rpcc/__init__.py
rpcc/__main__.py
rpcc/arguments.py
rpcc/console/__init__.py
rpcc/console/highlighter.py
rpcc/console/theme.py
rpcc/exceptions.py
rpcc/grammars/rpcc.lark
rpcc/ir.py
rpcc/meta.py
rpcc/parser.py
rpcc/rpcc.py
rpcc/transformers/__init__.py
rpcc/transformers/base.py
rpcc/transformers/cxx17/__init__.py
rpcc/transformers/cxx17/formatter.py
rpcc/transformers/cxx17/transformer.py
rpcc/transformers/cxx17/types.py
rpcc/transformers/factory.py
rpcc/version.py
rpcc-0.1.1.dist-info/entry_points.txt
rpcc-0.1.1.dist-info/COPYING
rpcc-0.1.1.dist-info/WHEEL
rpcc-0.1.1.dist-info/METADATA
rpcc-0.1.1.dist-info/RECORD
