Metadata-Version: 2.1
Name: rpcc
Version: 0.1.1
Summary: A compiler for Mercury-based RPCs
Home-page: https://storage.bsc.es/gitlab/hpc/rpcc
License: GPLv3
Author: Alberto Miranda
Author-email: alberto.miranda@bsc.es
Requires-Python: >=3.6.2,<4.0.0
Classifier: License :: OSI Approved :: GNU General Public License v3 (GPLv3)
Classifier: License :: Other/Proprietary License
Classifier: Programming Language :: Python :: 3
Classifier: Programming Language :: Python :: 3.10
Classifier: Programming Language :: Python :: 3.6
Classifier: Programming Language :: Python :: 3.7
Classifier: Programming Language :: Python :: 3.8
Classifier: Programming Language :: Python :: 3.9
Classifier: Topic :: Software Development :: Code Generators
Requires-Dist: lark (>=1.0.0,<2.0.0)
Requires-Dist: loguru (>=0.5.3,<0.6.0)
Requires-Dist: rich (>=10.15.1,<11.0.0)
Requires-Dist: typing-extensions (>=4.0.1,<5.0.0)
Project-URL: Documentation, https://storage.bsc.es/projects/rpcc
